[
  {
    "id": 87678840,
    "price": 1550000,
    "price_display": "£1,550,000",
    "address": "Hanworth Road, Hampton",
    "property_type": "Detached",
    "bedrooms": 4,
    "bathrooms": 2,
    "summary": "This imposing detached house is set on a bold plot occupying almost a quarter of an acre, and has been fully refurbished throughout to the highest of standards, combining traditional and modern features which complement this appealing family home. This stunning property is set back fro...",
    "url": "https://www.rightmove.co.uk/properties/87678840",
    "latitude": 51.42668,
    "longitude": -0.369608
  },
  {
    "id": 164515805,
    "price": 5000000,
    "price_display": "£5,000,000",
    "address": "Strawberry Vale, Strawberry Hill",
    "property_type": "Terraced",
    "bedrooms": 6,
    "bathrooms": 5,
    "summary": "Offers Over £5,000,000. Situated on the banks of the River Thames is this stunning six bedroom early Victorian villa that has been designed throughout by renowned local interior designer Claire Botha of Geek Vintique and benefits from having a 150ft riverside garden with a private mooring and boa...",
    "url": "https://www.rightmove.co.uk/properties/164515805",
    "latitude": 51.434626,
    "longitude": -0.329445
  },
  {
    "id": 164605847,
    "price": 5000000,
    "price_display": "£5,000,000",
    "address": "Strawberry Vale, Twickenham, London, TW1",
    "property_type": "House",
    "bedrooms": 6,
    "bathrooms": 5,
    "summary": "Enjoying a wonderful peaceful and relaxing setting, a quite magnificent and substantial family home with an exceptional interior backing directly onto the River Thames with moorings",
    "url": "https://www.rightmove.co.uk/properties/164605847",
    "latitude": 51.434576,
    "longitude": -0.329418
  },
  {
    "id": 171585815,
    "price": 4750000,
    "price_display": "£4,750,000",
    "address": "Strawberry Vale, Twickenham, TW1",
    "property_type": "Semi-Detached",
    "bedrooms": 6,
    "bathrooms": 5,
    "summary": "An exceptional and truly unique six-bedroom semi-detached early Victorian residence, offering over 4,000 sq. ft. of versatile and elegant accommodation across four floors. Positioned directly on the River Thames, the property enjoys breathtaking river views, a mature and secluded 170-foot garden ...",
    "url": "https://www.rightmove.co.uk/properties/171585815",
    "latitude": 51.435662,
    "longitude": -0.329936
  },
  {
    "id": 167014289,
    "price": 3750000,
    "price_display": "£3,750,000",
    "address": "Lebanon Park, Twickenham, TW1",
    "property_type": "Semi-Detached",
    "bedrooms": 5,
    "bathrooms": 4,
    "summary": "A beautifully presented and superbly situated double fronted home with a stunning garden.",
    "url": "https://www.rightmove.co.uk/properties/167014289",
    "latitude": 51.448403,
    "longitude": -0.321062
  },
  {
    "id": 172072886,
    "price": 3750000,
    "price_display": "£3,750,000",
    "address": "Stanley Road, Teddington, TW11",
    "property_type": "Detached",
    "bedrooms": 6,
    "bathrooms": 5,
    "summary": "A handsome and substantial six bedroom double fronted detached home which has been comprehensively renovated throughout by the current owners, offering over 4,690 sq.ft. of living space. Situated within central Teddington and offered to the market with no forward chain.",
    "url": "https://www.rightmove.co.uk/properties/172072886",
    "latitude": 51.428408,
    "longitude": -0.341525
  },
  {
    "id": 171955754,
    "price": 3500000,
    "price_display": "£3,500,000",
    "address": "Cole Park Road, Twickenham",
    "property_type": "Detached",
    "bedrooms": 8,
    "bathrooms": 6,
    "summary": "Offering just under 5,000 sq ft of accommodation, this outstanding eight-bedroom detached home enjoys a gated driveway, large private garden, and a highly sought-after location.",
    "url": "https://www.rightmove.co.uk/properties/171955754",
    "latitude": 51.451395,
    "longitude": -0.329806
  },
  {
    "id": 172834127,
    "price": 3250000,
    "price_display": "£3,250,000",
    "address": "Richmond Road, St Margarets",
    "property_type": "Detached",
    "bedrooms": 5,
    "bathrooms": 2,
    "summary": "Offering superb views over Marble Hill Park, this stunning detached Victorian home offers a perfect blend of classic charm and modern luxury. Boasting almost 3,500sqft of accommodation, this property is ideal for a growing family or those who love to entertain. The spacious interior is flooded wi...",
    "url": "https://www.rightmove.co.uk/properties/172834127",
    "latitude": 51.451937,
    "longitude": -0.316533
  },
  {
    "id": 159742634,
    "price": 3250000,
    "price_display": "£3,250,000",
    "address": "Hampton Road, Teddington, TW11",
    "property_type": "Detached",
    "bedrooms": 5,
    "bathrooms": 4,
    "summary": "A beautifully proportioned double fronted detached Victorian family home and Coach House attractively offered to the market with no onward chain. ",
    "url": "https://www.rightmove.co.uk/properties/159742634",
    "latitude": 51.427978,
    "longitude": -0.348035
  },
  {
    "id": 172452527,
    "price": 3150000,
    "price_display": "£3,150,000",
    "address": "Lebanon Park, Twickenham, TW1",
    "property_type": "Semi-Detached",
    "bedrooms": 5,
    "bathrooms": 3,
    "summary": "A handsome home of great period integrity.",
    "url": "https://www.rightmove.co.uk/properties/172452527",
    "latitude": 51.44794,
    "longitude": -0.321284
  },
  {
    "id": 166619597,
    "price": 2950000,
    "price_display": "£2,950,000",
    "address": "St. James's Road, Hampton Hill, TW12",
    "property_type": "Detached",
    "bedrooms": 7,
    "bathrooms": 4,
    "summary": "Tucked away on a peaceful residential street in the heart of Hampton Hill, Wayside is a truly distinguished Victorian residence offering a rare blend of grandeur, comfort, and charm. Surrounded by mature gardens and approached via a paved block driveway, this impressive seven-bedroom detached hom...",
    "url": "https://www.rightmove.co.uk/properties/166619597",
    "latitude": 51.429584,
    "longitude": -0.362551
  },
  {
    "id": 172404965,
    "price": 2750000,
    "price_display": "£2,750,000",
    "address": "Twickenham Road, Teddington",
    "property_type": "Detached",
    "bedrooms": 5,
    "bathrooms": 3,
    "summary": "The Coach House is a rare property in the heart of Teddington. With over 3000sq' across two floors, this 5 bedroom detached home provides spacious lateral living. Enjoying the privacy and security of being fully walled and gated, there's a sunny garden and large front yard with an abundance of ga...",
    "url": "https://www.rightmove.co.uk/properties/172404965",
    "latitude": 51.432914,
    "longitude": -0.329654
  },
  {
    "id": 170893880,
    "price": 2600000,
    "price_display": "£2,600,000",
    "address": "Strawberry Vale, Twickenham",
    "property_type": "Semi-Detached",
    "bedrooms": 5,
    "bathrooms": 2,
    "summary": "This rare and impressive semi-detached family home boasts a large garden backing directly onto the banks of the River Thames, complete with mooring for two boats. Arranged over three floors, the property offers five generously sized bedrooms, a wrap-around kitchen/dining area and a separate util...",
    "url": "https://www.rightmove.co.uk/properties/170893880",
    "latitude": 51.437469,
    "longitude": -0.330864
  },
  {
    "id": 172042181,
    "price": 2600000,
    "price_display": "£2,600,000",
    "address": "Claremont Road, Twickenham, TW1",
    "property_type": "Semi-Detached",
    "bedrooms": 5,
    "bathrooms": 3,
    "summary": "A beautifully appointed and superbly located family home.",
    "url": "https://www.rightmove.co.uk/properties/172042181",
    "latitude": 51.452983,
    "longitude": -0.317476
  },
  {
    "id": 167862080,
    "price": 2500000,
    "price_display": "£2,500,000",
    "address": "Poulett Gardens, Twickenham",
    "property_type": "Semi-Detached",
    "bedrooms": 5,
    "bathrooms": 3,
    "summary": "Offered with no onward chain and renovated to an exceptional standard throughout by the current owner, this stunning home boasts five bedrooms, three bath/shower rooms, a downstairs W.C, a utility room and off street parking to the front.",
    "url": "https://www.rightmove.co.uk/properties/167862080",
    "latitude": 51.444884,
    "longitude": -0.33109
  },
  {
    "id": 171911885,
    "price": 2400000,
    "price_display": "£2,400,000",
    "address": "Cassilis Road, St Margarets",
    "property_type": "Detached",
    "bedrooms": 5,
    "bathrooms": 3,
    "summary": "Newly refurbished Detached 5 bedroom home with driveway parking and access from both sides of the house to the 84ft west facing rear garden. Situated in a popular residential area just 0.3 miles from St Margarets village shops, cafes and train station and within 0.7 miles of St Stephens, St Mary'...",
    "url": "https://www.rightmove.co.uk/properties/171911885",
    "latitude": 51.45689,
    "longitude": -0.31985
  },
  {
    "id": 171660500,
    "price": 2400000,
    "price_display": "£2,400,000",
    "address": "Cassilis Road, Twickenham",
    "property_type": "House",
    "bedrooms": 5,
    "bathrooms": 3,
    "summary": "A beautifully renovated and stylish five-bedroom detached family home, ideally located in the heart of St Margarets village. Cassilis Road is a convenient location with easy access to the village, train station and River Thames.",
    "url": "https://www.rightmove.co.uk/properties/171660500",
    "latitude": 51.456765,
    "longitude": -0.319521
  },
  {
    "id": 87648384,
    "price": 2250000,
    "price_display": "£2,250,000",
    "address": "Clive Road, Twickenham, TW1",
    "property_type": "Detached",
    "bedrooms": 5,
    "bathrooms": 4,
    "summary": "Beautifully refurbished and thoughtfully extended five bedroom detached home in a cul-de-sac location off Strawberry Vale with the River Thames within 0.2 mile.",
    "url": "https://www.rightmove.co.uk/properties/87648384",
    "latitude": 51.434761,
    "longitude": -0.331713
  },
  {
    "id": 172819688,
    "price": 2250000,
    "price_display": "£2,250,000",
    "address": "Clive Road, Twickenham TW1",
    "property_type": "Detached",
    "bedrooms": 5,
    "bathrooms": 4,
    "summary": "An exceptional five bedroom home that has been meticulously remodeled, extended and finished to an outstanding standard throughout, offering beautifully designed living spaces and luxury detailing. Behind its attractive façade, the property has been completely transformed to create a stylish and...",
    "url": "https://www.rightmove.co.uk/properties/172819688",
    "latitude": 51.434688,
    "longitude": -0.332443
  },
  {
    "id": 150811691,
    "price": 2250000,
    "price_display": "£2,250,000",
    "address": "Whitton Road, Hounslow",
    "property_type": "House Share",
    "bedrooms": 9,
    "bathrooms": 7,
    "summary": "Introducing a unique investment opportunity: the dynamic duo of 60 Whitton and 62 Whitton Road, offered as a package deal. Nestled within a prime location, these properties boast a combined total of seven units, offering a diverse range of living spaces to suit various needs. 60 Whitton,.",
    "url": "https://www.rightmove.co.uk/properties/150811691",
    "latitude": 51.464397,
    "longitude": -0.362582
  },
  {
    "id": 87425226,
    "price": 2250000,
    "price_display": "£2,250,000",
    "address": "Walpole Road, Twickenham, TW2",
    "property_type": "Semi-Detached",
    "bedrooms": 4,
    "bathrooms": 3,
    "summary": "A handsome and substantial red brick Edwardian property which provides well balanced, generous and beautifully presented family accommodation.",
    "url": "https://www.rightmove.co.uk/properties/87425226",
    "latitude": 51.440857,
    "longitude": -0.34306
  },
  {
    "id": 167304236,
    "price": 2150000,
    "price_display": "£2,150,000",
    "address": "Bushy Park Gardens, Teddington",
    "property_type": "Detached",
    "bedrooms": 5,
    "bathrooms": 2,
    "summary": "Situated in the highly sought-after Bushy Park Gardens, this rarely available detached home offers an exciting opportunity to acquire a substantial family home with potential for modernisation. Set back from the road with off-street parking is this elegant property positioned on a generous plot f...",
    "url": "https://www.rightmove.co.uk/properties/167304236",
    "latitude": 51.427465,
    "longitude": -0.349944
  },
  {
    "id": 171522431,
    "price": 2000000,
    "price_display": "£2,000,000",
    "address": "Popes Grove, Twickenham, TW1",
    "property_type": "Semi-Detached",
    "bedrooms": 6,
    "bathrooms": 3,
    "summary": "This beautifully presented Edwardian family home offers a rare blend of timeless period charm and refined modern living, set in a highly desirable location close to outstanding schools, transport links and the river.",
    "url": "https://www.rightmove.co.uk/properties/171522431",
    "latitude": 51.44188,
    "longitude": -0.334696
  },
  {
    "id": 172544282,
    "price": 2000000,
    "price_display": "£2,000,000",
    "address": "Stanley Road, Teddington, TW11",
    "property_type": "Semi-Detached",
    "bedrooms": 6,
    "bathrooms": 5,
    "summary": "\"An inviting period residence located on one of Teddington’s well-regarded roads, this property may not come up again in your lifetime as it possesses the sought after blend of character, space and position that form the 'forever' home. . .\" Aaron - Co-Owner, Devenports. ",
    "url": "https://www.rightmove.co.uk/properties/172544282",
    "latitude": 51.429277,
    "longitude": -0.343011
  },
  {
    "id": 170644247,
    "price": 2000000,
    "price_display": "£2,000,000",
    "address": "Trafalgar Road, Twickenham",
    "property_type": "Semi-Detached",
    "bedrooms": 5,
    "bathrooms": 1,
    "summary": "A substantial, elegant and beautifully presented Victorian family home located in a highly desirable road close to some excellent schools, Twickenham Green and the station. The sizeable entrance hall leads into a spacious reception room with a feature fireplace and attractive windows t...",
    "url": "https://www.rightmove.co.uk/properties/170644247",
    "latitude": 51.440936,
    "longitude": -0.348931
  },
  {
    "id": 167051102,
    "price": 1250000,
    "price_display": "£1,250,000",
    "address": "Court Way, Twickenham",
    "property_type": "Semi-Detached",
    "bedrooms": 5,
    "bathrooms": 2,
    "summary": "This fabulous family home has been extended and improved throughout, combining traditional and modern features complementing this highly appealing property. Located in a desirable area close to some popular schools. With well-proportioned living spaces over three levels and a pleasing...",
    "url": "https://www.rightmove.co.uk/properties/167051102",
    "latitude": 51.45142,
    "longitude": -0.335432
  },
  {
    "id": 170814692,
    "price": 2000000,
    "price_display": "£2,000,000",
    "address": "Lynton Close, Isleworth, TW7",
    "property_type": "Semi-Detached",
    "bedrooms": 6,
    "bathrooms": 5,
    "summary": "An exceptional semi-detached home occupying a corner plot, offering over 3,000 sq ft of high-specification accommodation including a self-contained summer house with sauna, private garden, off-street parking and garage",
    "url": "https://www.rightmove.co.uk/properties/170814692",
    "latitude": 51.463902,
    "longitude": -0.332489
  },
  {
    "id": 172542926,
    "price": 1900000,
    "price_display": "£1,900,000",
    "address": "Waldegrave Road, Teddington, TW11",
    "property_type": "Semi-Detached",
    "bedrooms": 5,
    "bathrooms": 3,
    "summary": "\"Spacious, elegant and effortlessly practical — this is a home designed to grow with you. A handsome five-bedroom period home extending to approximately 2,500 sq ft, perfectly positioned on one of Teddington’s most sought-after roads. . .\" Ryan - Branch Manager, Devenports.<...",
    "url": "https://www.rightmove.co.uk/properties/172542926",
    "latitude": 51.431528,
    "longitude": -0.338348
  },
  {
    "id": 171822734,
    "price": 1900000,
    "price_display": "£1,900,000",
    "address": "Brewery Lane, Twickenham, TW1",
    "property_type": "Terraced",
    "bedrooms": 5,
    "bathrooms": 4,
    "summary": "A luxurious six bedroom home set in an exclusive gated mews with two private off street parking spaces and west facing garden.",
    "url": "https://www.rightmove.co.uk/properties/171822734",
    "latitude": 51.449658,
    "longitude": -0.333386
  },
  {
    "id": 163770647,
    "price": 1850000,
    "price_display": "£1,850,000",
    "address": "Church Road, Teddington, Middlesex, TW11",
    "property_type": "Terraced",
    "bedrooms": 5,
    "bathrooms": 2,
    "summary": "A truly exceptional five-bedroom family home, steeped in history, having previously served as the local doctor's surgery.",
    "url": "https://www.rightmove.co.uk/properties/163770647",
    "latitude": 51.427112,
    "longitude": -0.336901
  },
  {
    "id": 164535968,
    "price": 1850000,
    "price_display": "£1,850,000",
    "address": "Windmill Road, Hampton Hill",
    "property_type": "House",
    "bedrooms": 4,
    "bathrooms": 4,
    "summary": "\"The Windmill\" - this exceptional period conversion of The Windmill Public House, originally built in 1868, has been expertly transformed into a stunning family home, blending historic charm with modern sophistication.",
    "url": "https://www.rightmove.co.uk/properties/164535968",
    "latitude": 51.427773,
    "longitude": -0.362254
  },
  {
    "id": 169119293,
    "price": 1850000,
    "price_display": "£1,850,000",
    "address": "Cole Park Road, Twickenham, TW1",
    "property_type": "Detached",
    "bedrooms": 5,
    "bathrooms": 3,
    "summary": "This impressive detached family home offers over 3500 sq. ft. of thoughtfully balanced accommodation across three floors, combining generous proportions with practical, flexible family living. Ground Floor On the ground floor, a grand entrance hallway, currently arranged as a form...",
    "url": "https://www.rightmove.co.uk/properties/169119293",
    "latitude": 51.456577,
    "longitude": -0.329503
  },
  {
    "id": 171379655,
    "price": 1850000,
    "price_display": "£1,850,000",
    "address": "Amyand Park Road, St Margarets, Twickenham, TW1",
    "property_type": "Detached",
    "bedrooms": 5,
    "bathrooms": 3,
    "summary": "A beautifully enhanced detached family home with detached office, annexe and garage, set in the very heart of St Margarets village and offered to the market with no onward chain. ",
    "url": "https://www.rightmove.co.uk/properties/171379655",
    "latitude": 51.454223,
    "longitude": -0.32137
  },
  {
    "id": 165318251,
    "price": 1850000,
    "price_display": "£1,850,000",
    "address": "Cambridge Road, Teddington",
    "property_type": "House",
    "bedrooms": 4,
    "bathrooms": 3,
    "summary": "Set moments from Teddington High Street is this impressive semi-detached period family home. Offered with off street parking, two reception rooms and an open plan kitchen/dining room.",
    "url": "https://www.rightmove.co.uk/properties/165318251",
    "latitude": 51.431568,
    "longitude": -0.333024
  },
  {
    "id": 154982522,
    "price": 1850000,
    "price_display": "£1,850,000",
    "address": "Windmill Road, Hampton Hill, TW12",
    "property_type": "Semi-Detached",
    "bedrooms": 4,
    "bathrooms": 3,
    "summary": "\"For any buyer looking up to the £2,000,000 mark in the Hampton Hill or Teddington area, it is without question you will struggle to find a superior opportunity than 'The Windmill'. At this price point, the spec & location are simply unmatched when comparing the market currently . ...",
    "url": "https://www.rightmove.co.uk/properties/154982522",
    "latitude": 51.427818,
    "longitude": -0.362239
  },
  {
    "id": 170573810,
    "price": 1815000,
    "price_display": "£1,815,000",
    "address": "Hampton Road, Twickenham",
    "property_type": "Semi-Detached",
    "bedrooms": 5,
    "bathrooms": 4,
    "summary": "This stunning Victorian semi detached house, spanning over 2,600 square feet, seamlessly blends period charm with modern luxury. Featuring five double bedrooms and generous living spaces, off street parking for multiple cars and secluded back garden.",
    "url": "https://www.rightmove.co.uk/properties/170573810",
    "latitude": 51.441717,
    "longitude": -0.345084
  },
  {
    "id": 159596501,
    "price": 1799950,
    "price_display": "£1,799,950",
    "address": "Waldegrave Road, Strawberry hill, Twickenham, TW1",
    "property_type": "Detached",
    "bedrooms": 5,
    "bathrooms": 3,
    "summary": "A substantial & characterful Edwardian detached house with over 2800sq ft including a double garage. It offers private, walled gardens surrounding the property. With five bedrooms there are two utility rooms and the living space offers three grand rooms",
    "url": "https://www.rightmove.co.uk/properties/159596501",
    "latitude": 51.433523,
    "longitude": -0.338014
  },
  {
    "id": 171749147,
    "price": 1770000,
    "price_display": "£1,770,000",
    "address": "Clive Road, Strawberry Hill, Twickenham, TW1",
    "property_type": "Detached",
    "bedrooms": 5,
    "bathrooms": 2,
    "summary": "Offering stylish and contemporary interiors throughout, this superb 5 bedroom family home boasts bright accommodation and is arranged over 3 floors with a gorgeous rear garden.",
    "url": "https://www.rightmove.co.uk/properties/171749147",
    "latitude": 51.43495,
    "longitude": -0.33231
  },
  {
    "id": 170777294,
    "price": 1770000,
    "price_display": "£1,770,000",
    "address": "Clive Road, Strawberry Hill",
    "property_type": "Detached",
    "bedrooms": 5,
    "bathrooms": 2,
    "summary": "This fantastic five bedroom detached 1930's family home is in excellent condition throughout and it benefits from having two bath/shower rooms, a stylish open plan kitchen/family room, downstairs W.C and off street parking to the front.",
    "url": "https://www.rightmove.co.uk/properties/170777294",
    "latitude": 51.434883,
    "longitude": -0.333113
  },
  {
    "id": 172141676,
    "price": 1750000,
    "price_display": "£1,750,000",
    "address": "Teddington Park, Teddington",
    "property_type": "Semi-Detached",
    "bedrooms": 4,
    "bathrooms": 1,
    "summary": "Spacious and filled with natural light, this impressive family home offers four double-bedrooms in the heart of Teddington. Offered to the market with over 1,900 Sq. Ft, the layout opens up beautifully with generous proportions and multiple receptions. This Teddington Park home is ideal for both ...",
    "url": "https://www.rightmove.co.uk/properties/172141676",
    "latitude": 51.430012,
    "longitude": -0.334387
  },
  {
    "id": 171417401,
    "price": 1750000,
    "price_display": "£1,750,000",
    "address": "Teddington Park, Teddington, TW11",
    "property_type": "Semi-Detached",
    "bedrooms": 5,
    "bathrooms": 3,
    "summary": "Exceptional five bedroom semi-detached period residence which has retained many character features and is located in a much requested residential road, in the heart of Teddington, close to the High Street and river. The property has an attractive elegant front porch, ornate architraves...",
    "url": "https://www.rightmove.co.uk/properties/171417401",
    "latitude": 51.43077,
    "longitude": -0.333657
  },
  {
    "id": 171386171,
    "price": 1750000,
    "price_display": "£1,750,000",
    "address": "Teddington Park, Teddington",
    "property_type": "House",
    "bedrooms": 5,
    "bathrooms": 3,
    "summary": "This well-balanced home offers excellent accommodation across three floors, blending character, comfort, and practicality for family living.",
    "url": "https://www.rightmove.co.uk/properties/171386171",
    "latitude": 51.43093,
    "longitude": -0.333311
  },
  {
    "id": 172782971,
    "price": 1750000,
    "price_display": "£1,750,000",
    "address": "Teddington Park, Teddington",
    "property_type": "Semi-Detached",
    "bedrooms": 5,
    "bathrooms": 2,
    "summary": "This house offers a great sense of space, boasting large rooms with high ceilings, original period features and offers potential to extend the ground floor. This is an ideal property for a growing family.",
    "url": "https://www.rightmove.co.uk/properties/172782971",
    "latitude": 51.430818,
    "longitude": -0.333455
  },
  {
    "id": 172757939,
    "price": 1750000,
    "price_display": "£1,750,000",
    "address": "Teddington Park, Teddington",
    "property_type": "Semi-Detached",
    "bedrooms": 5,
    "bathrooms": 2,
    "summary": "Located on a highly sought-after, tree-lined avenue in central Teddington, just moments from Teddington High Street, this elegant five-bedroom Edwardian residence offers beautifully proportioned accommodation rich in original period detail and benefitting from off street parking. An at...",
    "url": "https://www.rightmove.co.uk/properties/172757939",
    "latitude": 51.430819,
    "longitude": -0.333444
  },
  {
    "id": 172634666,
    "price": 1750000,
    "price_display": "£1,750,000",
    "address": "Cole Park Road, St Margarets",
    "property_type": "Detached",
    "bedrooms": 5,
    "bathrooms": 2,
    "summary": "A rare and expansive family home in the heart of St Margarets, blending character, versatility and modern living across generous proportions. This impressive property offers well-balanced accommodation for everyday life and entertaining alike, with a layout that simply works for today's way of li...",
    "url": "https://www.rightmove.co.uk/properties/172634666",
    "latitude": 51.457762,
    "longitude": -0.330089
  },
  {
    "id": 172058267,
    "price": 1695000,
    "price_display": "£1,695,000",
    "address": "Uxbridge Road, Hampton Hill, TW12",
    "property_type": "Detached",
    "bedrooms": 6,
    "bathrooms": 3,
    "summary": "\"A combination of intricately planned space and unapologetically tasteful luxury, spanning in excess of 3400 square feet just minutes from Bushy Park. Dare we pose the question, is this Hampton's best opportunity? . . .\" James (Devenports Co-Owner) This home is a true repres...",
    "url": "https://www.rightmove.co.uk/properties/172058267",
    "latitude": 51.432304,
    "longitude": -0.367926
  },
  {
    "id": 172390214,
    "price": 1675000,
    "price_display": "£1,675,000",
    "address": "Elmfield Avenue, Teddington",
    "property_type": "House",
    "bedrooms": 4,
    "bathrooms": 2,
    "summary": "Centrally located this double fronted home is a must see. It offers over 2100sq ft with off street parking and flexible living space throughout along with being well located for local schools.",
    "url": "https://www.rightmove.co.uk/properties/172390214",
    "latitude": 51.430552,
    "longitude": -0.331446
  },
  {
    "id": 168899102,
    "price": 1675000,
    "price_display": "£1,675,000",
    "address": "Anlaby Road, Teddington, TW11",
    "property_type": "Semi-Detached",
    "bedrooms": 4,
    "bathrooms": 2,
    "summary": "This beautful four-bedroom period home is the all round family home in TW11, fully extended offered with off street parking and a huge rear garden ticks all the boxes. The house compromises a large open plan living / kitchen / dining area, a separate front reception space, Utility and downstairs ...",
    "url": "https://www.rightmove.co.uk/properties/168899102",
    "latitude": 51.430118,
    "longitude": -0.346714
  },
  {
    "id": 169171634,
    "price": 1650000,
    "price_display": "£1,650,000",
    "address": "Alpha Road, Middlesex",
    "property_type": "End of Terrace",
    "bedrooms": 5,
    "bathrooms": 3,
    "summary": "This stunning five-bedroom family home has been fully refurbished to an exceptional standard throughout, offering the perfect blend of style, space, and modern living. Every detail has been carefully considered to create a luxurious yet practical home ideal for family life. Upon enteri...",
    "url": "https://www.rightmove.co.uk/properties/169171634",
    "latitude": 51.429264,
    "longitude": -0.352396
  },
  {
    "id": 171884006,
    "price": 1650000,
    "price_display": "£1,650,000",
    "address": "Alpha Road, Teddington, TW11",
    "property_type": "End of Terrace",
    "bedrooms": 5,
    "bathrooms": 3,
    "summary": "Five bedroom remodelled home with sleek design and finish with west facing lawned garden extending to 51 ft.",
    "url": "https://www.rightmove.co.uk/properties/171884006",
    "latitude": 51.429246,
    "longitude": -0.352499
  }
]